src/IFC.py
src/Image-f-c.py
src/__init__.py
Image_f_c-0.1.6.dist-info/METADATA
Image_f_c-0.1.6.dist-info/WHEEL
Image_f_c-0.1.6.dist-info/top_level.txt
Image_f_c-0.1.6.dist-info/RECORD
