Metadata-Version: 2.1
Name: Image-f-c
Version: 0.1.6
Summary: Convert all files directly under the directory to any music file.
Home-page: https://github.com/Ryomo0797/AudioAlchemist.git
Download-URL: https://github.com/Ryomo0797/AudioAlchemist.git
Author: Goki Nagata
Author-email: s2222068@stu.musashino-u.ac.jp
Maintainer: Goki Nagata
Maintainer-email: s2222068@stu.musashino-u.ac.jp
License: MIT
Keywords: PIL,image,file,png,jpeg,bmp
Classifier: License :: OSI Approved :: MIT License
Classifier: Programming Language :: Python :: 3.6
Requires-Dist: pillow >=0.25.1
